{
  "last_updated": "2026-04-18T04:17:02",
  "last_updated_display": "April 18, 2026 at 04:17 AM",
  "mosques": [
    {
      "id": "icw",
      "name": "Islamic Center of Wylie (ICW)",
      "address": "3990 Lakeway Dr, St. Paul, TX 75098",
      "website": "https://icwtx.org",
      "phone": "",
      "status": "live",
      "prayers": {
        "fajr": {
          "adhan": "05:41 AM",
          "iqamah": "02:15 PM"
        },
        "dhuhr": {
          "adhan": "01:26 PM",
          "iqamah": "01:26 PM"
        },
        "asr": {
          "adhan": "05:04 PM",
          "iqamah": "05:04 PM"
        },
        "maghrib": {
          "adhan": "05:41 AM",
          "iqamah": "02:15 PM"
        },
        "isha": {
          "adhan": "05:41 AM",
          "iqamah": "02:15 PM"
        }
      },
      "jumuah": [
        "2:15 PM"
      ]
    },
    {
      "id": "epic",
      "name": "EPIC Masjid",
      "address": "4700 14th Street, Plano, TX 75074",
      "website": "https://epicmasjid.org",
      "phone": "(214) 396-1943",
      "status": "live",
      "prayers": {
        "fajr": {
          "adhan": "05:43 AM",
          "iqamah": "06:00 AM"
        },
        "dhuhr": {
          "adhan": "01:27 PM",
          "iqamah": "02:00 PM"
        },
        "asr": {
          "adhan": "05:05 PM",
          "iqamah": "06:15 PM"
        },
        "maghrib": {
          "adhan": "07:59 PM",
          "iqamah": "08:09 PM"
        },
        "isha": {
          "adhan": "09:10 PM",
          "iqamah": "09:30 PM"
        }
      },
      "jumuah": [
        "01:45 PM",
        "03:15 PM"
      ]
    },
    {
      "id": "iaqc",
      "name": "IAQC - Islamic Association of Quad Cities",
      "address": "3800 Parker Rd, St. Paul, TX 75098",
      "website": "https://iaqctx.org",
      "phone": "(214) 435-8961",
      "status": "hardcoded",
      "prayers": {
        "fajr": {
          "adhan": "6:00 AM",
          "iqamah": "6:00 AM"
        },
        "dhuhr": {
          "adhan": "2:00 PM",
          "iqamah": "2:00 PM"
        },
        "asr": {
          "adhan": "6:00 PM",
          "iqamah": "6:00 PM"
        },
        "maghrib": {
          "adhan": "8:04 PM",
          "iqamah": "8:04 PM"
        },
        "isha": {
          "adhan": "9:30 PM",
          "iqamah": "9:30 PM"
        }
      },
      "jumuah": [
        "1:30 PM",
        "2:30 PM"
      ]
    },
    {
      "id": "iacc",
      "name": "Plano Masjid (IACC)",
      "address": "6401 Independence Pkwy, Plano, TX 75023",
      "website": "https://planomasjid.org",
      "phone": "972-491-5800",
      "status": "hardcoded",
      "prayers": {
        "fajr": {
          "adhan": "6:00 AM",
          "iqamah": "6:00 AM"
        },
        "dhuhr": {
          "adhan": "2:00 PM",
          "iqamah": "2:00 PM"
        },
        "asr": {
          "adhan": "6:15 PM",
          "iqamah": "6:15 PM"
        },
        "maghrib": {
          "adhan": "8:09 PM",
          "iqamah": "8:09 PM"
        },
        "isha": {
          "adhan": "9:30 PM",
          "iqamah": "9:30 PM"
        }
      },
      "jumuah": [
        "1:45 PM",
        "3:00 PM"
      ]
    },
    {
      "id": "faizan",
      "name": "Masjid Faizan-E-Madinah",
      "address": "641 W Brown St, Wylie, TX 75098",
      "website": "https://www.facebook.com/faizanemadinahdallas/",
      "phone": "",
      "status": "hardcoded",
      "prayers": {
        "fajr": {
          "adhan": "6:15 AM",
          "iqamah": "6:15 AM"
        },
        "dhuhr": {
          "adhan": "2:00 PM",
          "iqamah": "2:00 PM"
        },
        "asr": {
          "adhan": "6:30 PM",
          "iqamah": "6:30 PM"
        },
        "maghrib": {
          "adhan": "7:57 PM",
          "iqamah": "7:57 PM"
        },
        "isha": {
          "adhan": "9:45 PM",
          "iqamah": "9:45 PM"
        }
      },
      "jumuah": [
        "2:00 PM"
      ]
    }
  ]
}